{"assets/fonts/ComicNeue-Bold.ttf":["assets/fonts/ComicNeue-Bold.ttf"],"assets/fonts/ComicNeue-BoldItalic.ttf":["assets/fonts/ComicNeue-BoldItalic.ttf"],"assets/fonts/ComicNeue-Italic.ttf":["assets/fonts/ComicNeue-Italic.ttf"],"assets/fonts/ComicNeue-Light.ttf":["assets/fonts/ComicNeue-Light.ttf"],"assets/fonts/ComicNeue-LightItalic.ttf":["assets/fonts/ComicNeue-LightItalic.ttf"],"assets/fonts/ComicNeue-Regular.ttf":["assets/fonts/ComicNeue-Regular.ttf"],"assets/fonts/Kalam-Bold.ttf":["assets/fonts/Kalam-Bold.ttf"],"assets/fonts/Kalam-Light.ttf":["assets/fonts/Kalam-Light.ttf"],"assets/fonts/Kalam-Regular.ttf":["assets/fonts/Kalam-Regular.ttf"],"assets/fonts/Ubuntu-Bold.ttf":["assets/fonts/Ubuntu-Bold.ttf"],"assets/fonts/Ubuntu-BoldItalic.ttf":["assets/fonts/Ubuntu-BoldItalic.ttf"],"assets/fonts/Ubuntu-Italic.ttf":["assets/fonts/Ubuntu-Italic.ttf"],"assets/fonts/Ubuntu-Light.ttf":["assets/fonts/Ubuntu-Light.ttf"],"assets/fonts/Ubuntu-LightItalic.ttf":["assets/fonts/Ubuntu-LightItalic.ttf"],"assets/fonts/Ubuntu-Medium.ttf":["assets/fonts/Ubuntu-Medium.ttf"],"assets/fonts/Ubuntu-MediumItalic.ttf":["assets/fonts/Ubuntu-MediumItalic.ttf"],"assets/fonts/Ubuntu-Regular.ttf":["assets/fonts/Ubuntu-Regular.ttf"],"assets/pngs/bg.png":["assets/pngs/bg.png"],"packages/cupertino_icons/assets/CupertinoIcons.ttf":["packages/cupertino_icons/assets/CupertinoIcons.ttf"]}